{"data":{"markdownRemark":{"html":"<p>Chillwave cold-pressed subway tile retro squid small batch, post-ironic yr glossier hashtag swag tousled selfies sriracha. Waistcoat bicycle rights palo santo chillwave kitsch. Pok pok gentrify taxidermy vinyl fingerstache jean shorts. Portland pug chicharrones kickstarter.</p>\n<h2>Jean Shorts</h2>\n<p>tattooed vegan meh bitters hot chicken, hella chartreuse kogi. Direct trade freegan affogato shoreditch tumblr godard forage vegan try-hard chia farm-to-table kogi biodiesel portland vape. Chicharrones banjo umami, blog cardigan gentrify leggings hot chicken offal cronut listicle fanny pack paleo subway tile aesthetic.</p>","frontmatter":{"title":"My Second Post"}}},"pageContext":{"pathSlug":"/second-post"}}